plex_sub_downloader/PlexSubDownloader.py
plex_sub_downloader/PlexWebhookEvent.py
plex_sub_downloader/__init__.py
plex_sub_downloader/config.schema.json
plex_sub_downloader/plexHelper.py
plex_sub_downloader/plex_sub_downloader.py
plex_sub_downloader/subliminalHelper.py
plex_sub_downloader-0.3.1.dist-info/LICENSE.txt
plex_sub_downloader-0.3.1.dist-info/METADATA
plex_sub_downloader-0.3.1.dist-info/WHEEL
plex_sub_downloader-0.3.1.dist-info/entry_points.txt
plex_sub_downloader-0.3.1.dist-info/top_level.txt
plex_sub_downloader-0.3.1.dist-info/RECORD
