Metadata-Version: 2.1
Name: plex_sub_downloader
Version: 0.3.1
Summary: A (hopefully) straightforward cli tool for downloading subtitles for newly added Plex media.
Author-email: mjvotaw <mjvotaw@gmail.com>
Project-URL: Homepage, https://github.com/mjvotaw/plex-sub-downloader
Project-URL: Bug Tracker, https://github.com/mjvotaw/plex-sub-downloader/issues
Classifier: Programming Language :: Python :: 3
Classifier: License :: OSI Approved :: MIT License
Classifier: Operating System :: OS Independent
Requires-Python: >=3.8
License-File: LICENSE.txt
Requires-Dist: PlexAPI >=4.15.5
Requires-Dist: subliminal >=2.1.0
Requires-Dist: Flask >=2.0.0
Requires-Dist: waitress >=2.1.2
Requires-Dist: jsonschema
